synchronous_fifo.v
module synchronous_fifo #(
    parameter DATA_WIDTH = 8,
    parameter DEPTH = 16
)(
    input wire clk,                   // Clock input
    input wire rst,                   // Reset (active high)
    input wire wr_en,                 // Write enable
    input wire rd_en,                 // Read enable
    input wire [DATA_WIDTH-1:0] din,  // Data input
    output reg [DATA_WIDTH-1:0] dout, // Data output
    output reg full,                  // Full flag
    output reg empty                  // Empty flag
);

    // Internal registers
    reg [DATA_WIDTH-1:0] memory [0:DEPTH-1]; // Memory array
    reg [3:0] wr_ptr = 0;                    // Write pointer (4 bits for DEPTH = 16)
    reg [3:0] rd_ptr = 0;                    // Read pointer (4 bits for DEPTH = 16)
    reg [4:0] fifo_count = 0;                // Count of elements in FIFO (5 bits for DEPTH up to 16)

    // Write operation
    always @(posedge clk or posedge rst) begin
        if (rst) begin
            wr_ptr <= 0;
        end else if (wr_en && !full) begin
            memory[wr_ptr] <= din;
            wr_ptr <= wr_ptr + 1;
        end
    end

    // Read operation
    always @(posedge clk or posedge rst) begin
        if (rst) begin
            rd_ptr <= 0;
            dout <= 0;
        end else if (rd_en && !empty) begin
            dout <= memory[rd_ptr];
            rd_ptr <= rd_ptr + 1;
        end
    end

// FIFO count and flag management
always @(posedge clk or posedge rst) begin
    if (rst) begin
        fifo_count <= 0;
        full <= 0;
        empty <= 1;
    end else begin
        // Update count based on read and write enables
        if (wr_en && !full && !(rd_en && !empty)) begin
            fifo_count <= fifo_count + 1; // Write only
        end else if (rd_en && !empty && !(wr_en && !full)) begin
            fifo_count <= fifo_count - 1; // Read only
        end

        // Update full and empty flags
        full <= (fifo_count == DEPTH - 1 && wr_en && !rd_en) || (fifo_count == DEPTH);
        empty <= (fifo_count == 1 && rd_en && !wr_en) || (fifo_count == 0);
    end
end


endmodule

tb_synchronous_fifo.v
`timescale 1ns / 1ps

module tb_synchronous_fifo;

    // Parameters
    parameter DATA_WIDTH = 8;
    parameter DEPTH = 16;

    // Testbench Signals
    reg clk;
    reg rst;
    reg wr_en;
    reg rd_en;
    reg [DATA_WIDTH-1:0] din;
    wire [DATA_WIDTH-1:0] dout;
    wire full;
    wire empty;

    // Instantiate the FIFO
    synchronous_fifo #(
        .DATA_WIDTH(DATA_WIDTH),
        .DEPTH(DEPTH)
    ) uut (
        .clk(clk),
        .rst(rst),
        .wr_en(wr_en),
        .rd_en(rd_en),
        .din(din),
        .dout(dout),
        .full(full),
        .empty(empty)
    );

    // Clock generation
    initial begin
        $dumpfile("fifo_waveform.vcd"); // Specifies the name of the VCD file
        $dumpvars(0, tb_synchronous_fifo); // Dumps all signals in the testbench
        clk = 0;
        forever #5 clk = ~clk;  // 10 ns clock period
    end

    // Test procedure
    initial begin
        // Initialize signals
        rst = 1;
        wr_en = 0;
        rd_en = 0;
        din = 0;

        // Reset the FIFO
        #10 rst = 0;
        #10 rst = 1;  // Release reset
        #10 rst = 0;

        // Write data to the FIFO until it is full
        $display("Starting FIFO Write Operations");
        repeat (DEPTH) begin
            @(posedge clk);
            wr_en = 1;
            din = din + 1;
        end
        @(posedge clk);
        wr_en = 0;  // Stop writing

        // Check if FIFO is full
        if (full)
            $display("FIFO is full as expected.");
        else
            $display("Error: FIFO is not full!");

        // Read data from the FIFO until it is empty
        $display("Starting FIFO Read Operations");
        repeat (DEPTH) begin
            @(posedge clk);
            rd_en = 1;
        end
        @(posedge clk);
        rd_en = 0;  // Stop reading

        // Check if FIFO is empty
        if (empty)
            $display("FIFO is empty as expected.");
        else
            $display("Error: FIFO is not empty!");

        // Test random write and read operations
        $display("Testing Random Write and Read Operations");
        wr_en = 1; din = 8'hAA; @(posedge clk);
        wr_en = 1; din = 8'hBB; @(posedge clk);
        wr_en = 0; rd_en = 1; @(posedge clk);
        rd_en = 0;

        // Finish simulation
        $stop;
    end

endmodule

fifo_waveform.vcd
$date
	Tue Nov 05 08:39:17 2024
$end
$version
	Icarus Verilog
$end
$timescale
	1ps
$end
$scope module tb_synchronous_fifo $end
$var wire 1 ! full $end
$var wire 1 " empty $end
$var wire 8 # dout [7:0] $end
$var parameter 32 $ DATA_WIDTH $end
$var parameter 32 % DEPTH $end
$var reg 1 & clk $end
$var reg 8 ' din [7:0] $end
$var reg 1 ( rd_en $end
$var reg 1 ) rst $end
$var reg 1 * wr_en $end
$scope module uut $end
$var wire 1 & clk $end
$var wire 8 + din [7:0] $end
$var wire 1 ( rd_en $end
$var wire 1 ) rst $end
$var wire 1 * wr_en $end
$var parameter 32 , DATA_WIDTH $end
$var parameter 32 - DEPTH $end
$var reg 8 . dout [7:0] $end
$var reg 1 " empty $end
$var reg 5 / fifo_count [4:0] $end
$var reg 1 ! full $end
$var reg 4 0 rd_ptr [3:0] $end
$var reg 4 1 wr_ptr [3:0] $end
$upscope $end
$upscope $end
$enddefinitions $end
$comment Show the parameter values. $end
$dumpall
b10000 -
b1000 ,
b10000 %
b1000 $
$end
#0
$dumpvars
b0 1
b0 0
b0 /
b0 .
b0 +
0*
1)
0(
b0 '
0&
b0 #
1"
0!
$end
#5000
1&
#10000
0&
0)
#15000
1&
#20000
0&
1)
#25000
1&
#30000
0&
0)
#35000
b1 /
b1 1
b1 '
b1 +
1*
1&
#40000
0&
#45000
b10 1
0"
b10 /
b10 '
b10 +
1&
#50000
0&
#55000
b11 /
b11 1
b11 '
b11 +
1&
#60000
0&
#65000
b100 1
b100 /
b100 '
b100 +
1&
#70000
0&
#75000
b101 /
b101 1
b101 '
b101 +
1&
#80000
0&
#85000
b110 1
b110 /
b110 '
b110 +
1&
#90000
0&
#95000
b111 /
b111 1
b111 '
b111 +
1&
#100000
0&
#105000
b1000 1
b1000 /
b1000 '
b1000 +
1&
#110000
0&
#115000
b1001 /
b1001 1
b1001 '
b1001 +
1&
#120000
0&
#125000
b1010 1
b1010 /
b1010 '
b1010 +
1&
#130000
0&
#135000
b1011 /
b1011 1
b1011 '
b1011 +
1&
#140000
0&
#145000
b1100 1
b1100 /
b1100 '
b1100 +
1&
#150000
0&
#155000
b1101 /
b1101 1
b1101 '
b1101 +
1&
#160000
0&
#165000
b1110 1
b1110 /
b1110 '
b1110 +
1&
#170000
0&
#175000
b1111 /
b1111 1
b1111 '
b1111 +
1&
#180000
0&
#185000
b0 1
1!
b10000 /
b10000 '
b10000 +
1&
#190000
0&
#195000
0*
1&
#200000
0&
#205000
b1 0
b1 #
b1 .
b1111 /
1(
1&
#210000
0&
#215000
0!
b1110 /
b10 0
b10 #
b10 .
1&
#220000
0&
#225000
b11 0
b11 #
b11 .
b1101 /
1&
#230000
0&
#235000
b1100 /
b100 0
b100 #
b100 .
1&
#240000
0&
#245000
b101 0
b101 #
b101 .
b1011 /
1&
#250000
0&
#255000
b1010 /
b110 0
b110 #
b110 .
1&
#260000
0&
#265000
b111 0
b111 #
b111 .
b1001 /
1&
#270000
0&
#275000
b1000 /
b1000 0
b1000 #
b1000 .
1&
#280000
0&
#285000
b1001 0
b1001 #
b1001 .
b111 /
1&
#290000
0&
#295000
b110 /
b1010 0
b1010 #
b1010 .
1&
#300000
0&
#305000
b1011 0
b1011 #
b1011 .
b101 /
1&
#310000
0&
#315000
b100 /
b1100 0
b1100 #
b1100 .
1&
#320000
0&
#325000
b1101 0
b1101 #
b1101 .
b11 /
1&
#330000
0&
#335000
b10 /
b1110 0
b1110 #
b1110 .
1&
#340000
0&
#345000
b1111 0
b1111 #
b1111 .
b1 /
1&
#350000
0&
#355000
1"
b0 /
b0 0
b10000 #
b10000 .
1&
#360000
0&
#365000
b1 1
b1 /
b10101010 '
b10101010 +
1*
0(
1&
#370000
0&
#375000
0"
b10 /
b10 1
b10111011 '
b10111011 +
1&
#380000
0&
#385000
b1 0
b10101010 #
b10101010 .
b1 /
1(
0*
1&
